keboola/utils/__init__.py
keboola/utils/char_encoder.py
keboola/utils/date.py
keboola/utils/header_normalizer.py
keboola/utils/helpers.py
keboola.utils-1.1.2.dist-info/LICENSE
keboola.utils-1.1.2.dist-info/METADATA
keboola.utils-1.1.2.dist-info/WHEEL
keboola.utils-1.1.2.dist-info/top_level.txt
keboola.utils-1.1.2.dist-info/RECORD
