Metadata-Version: 2.1
Name: keboola.utils
Version: 1.1.2
Summary: General utility library for Python applications running in Keboola Connection environment
Home-page: https://github.com/keboola/python-utils
Author: Keboola KDS Team
Author-email: support@keboola.com
License: UNKNOWN
Project-URL: Documentation, https://htmlpreview.github.io/?https://raw.githubusercontent.com/keboola/python-utils/main/docs/api-html/utils/index.html
Platform: UNKNOWN
Classifier: Programming Language :: Python :: 3
Classifier: License :: OSI Approved :: MIT License
Classifier: Operating System :: OS Independent
Classifier: Intended Audience :: Developers
Classifier: Intended Audience :: Information Technology
Classifier: Intended Audience :: Education
Classifier: Topic :: Software Development :: Libraries
Classifier: Topic :: Software Development :: Libraries :: Python Modules
Classifier: Development Status :: 4 - Beta
Requires-Python: >=3.7
Requires-Dist: dateparser
Requires-Dist: pytz
Requires-Dist: camel-tools
